geoapps_utils/__init__.py
geoapps_utils/_version.py
geoapps_utils/base.py
geoapps_utils/driver/__init__.py
geoapps_utils/driver/data.py
geoapps_utils/driver/driver.py
geoapps_utils/driver/params.py
geoapps_utils/modelling/__init__.py
geoapps_utils/modelling/plates.py
geoapps_utils/param_sweeps/__init__.py
geoapps_utils/param_sweeps/driver.py
geoapps_utils/param_sweeps/generate.py
geoapps_utils/run.py
geoapps_utils/utils/__init__.py
geoapps_utils/utils/conversions.py
geoapps_utils/utils/formatters.py
geoapps_utils/utils/importing.py
geoapps_utils/utils/iterables.py
geoapps_utils/utils/locations.py
geoapps_utils/utils/logger.py
geoapps_utils/utils/numerical.py
geoapps_utils/utils/plotting.py
geoapps_utils/utils/reference.py
geoapps_utils/utils/transformations.py
geoapps_utils/utils/workspace.py
geoapps_utils-assets/__init__.py
geoapps_utils-assets/uijson/base.ui.json
geoapps_utils-0.6.0.dist-info/METADATA
geoapps_utils-0.6.0.dist-info/WHEEL
geoapps_utils-0.6.0.dist-info/licenses/LICENSE
geoapps_utils-0.6.0.dist-info/licenses/THIRD_PARTY_SOFTWARE.rst
geoapps_utils-0.6.0.dist-info/RECORD
