Metadata-Version: 2.4
Name: geoapps-utils
Version: 0.6.0
Summary: Utility functions to build applications supported by Mira Geoscience
License-Expression: MIT
License-File: LICENSE
License-File: THIRD_PARTY_SOFTWARE.rst
Keywords: geology,geophysics,data,interoperability
Author: Mira Geoscience
Author-email: support@mirageoscience.com
Maintainer: Dominique Fournier
Maintainer-email: dominiquef@mirageoscience.com
Requires-Python: >=3.10,<4.0
Classifier: Development Status :: 4 - Beta
Classifier: Intended Audience :: Science/Research
Classifier: Natural Language :: English
Classifier: Operating System :: MacOS
Classifier: Operating System :: Microsoft :: Windows
Classifier: Operating System :: POSIX
Classifier: Operating System :: Unix
Classifier: Programming Language :: Python :: 3
Classifier: Programming Language :: Python :: 3.10
Classifier: Programming Language :: Python :: 3.11
Classifier: Programming Language :: Python :: 3.12
Classifier: Programming Language :: Python :: 3.13
Classifier: Programming Language :: Python :: 3.14
Classifier: Topic :: Scientific/Engineering
Classifier: Topic :: Scientific/Engineering :: Mathematics
Classifier: Topic :: Scientific/Engineering :: Physics
Requires-Dist: geoh5py (>=0.12.0rc2,<0.13.dev)
Requires-Dist: matplotlib (>=3.8.4,<3.9.0)
Requires-Dist: numpy (>=1.26.0,<1.27.0)
Requires-Dist: pydantic (>=2.11,<2.12)
Requires-Dist: scipy (>=1.14.0,<1.15.0)
Project-URL: Homepage, https://www.mirageoscience.com/mining-industry-software/python-integration/
Project-URL: Repository, https://github.com/MiraGeoscience/geoapps-utils
